aintect/__init__.py
aintect/class_tab.py
aintect/common.py
aintect/main.py
aintect/model.py
aintect/notify.py
aintect/overlay.py
aintect-1.1.10.dist-info/METADATA
aintect-1.1.10.dist-info/WHEEL
aintect-1.1.10.dist-info/top_level.txt
aintect-1.1.10.dist-info/RECORD
