Metadata-Version: 2.4
Name: aintect
Version: 1.1.10
Author: Ainul Hakim
Author-email: Ainul Hakim <ainulhakimfizam@gmail.com>
Requires-Dist: pyside6
Requires-Dist: numpy
Requires-Dist: opencv-python
Requires-Dist: requests
